pyshipping/__init__.py
pyshipping/addressvalidation.py
pyshipping/binpack.py
pyshipping/binpack_simple.py
pyshipping/package.py
pyshipping/shipment.py
kuchbhi-0.1.dist-info/LICENSE
kuchbhi-0.1.dist-info/METADATA
kuchbhi-0.1.dist-info/WHEEL
kuchbhi-0.1.dist-info/top_level.txt
kuchbhi-0.1.dist-info/RECORD
