Metadata-Version: 2.1
Name: kuchbhi
Version: 0.1
Summary: kuch bhi ho rha hai
Home-page: https://github.com/hudora/pyShipping/
Maintainer: Rahul
Maintainer-email: raulsharma070894@gmail.com
License: UNKNOWN
Platform: UNKNOWN
Classifier: License :: OSI Approved :: BSD License
Classifier: Intended Audience :: Developers
Classifier: Programming Language :: Python
